vak_test_net/__init__.py
vak_test_net/network.py
vak_test_net-0.1.1.dist-info/LICENSE
vak_test_net-0.1.1.dist-info/METADATA
vak_test_net-0.1.1.dist-info/WHEEL
vak_test_net-0.1.1.dist-info/entry_points.txt
vak_test_net-0.1.1.dist-info/top_level.txt
vak_test_net-0.1.1.dist-info/RECORD
