Metadata-Version: 2.1
Name: vak-test-net
Version: 0.1.1
Summary: used to test the vak library (https://github.com/NickleDave/vak)
Home-page: https://github.com/NickleDave/vak_test_net
Author: David Nicholson
Author-email: dnicho4@emory.edu
License: BSD
Platform: UNKNOWN
Classifier: License :: OSI Approved :: BSD License
Classifier: Development Status :: 4 - Beta
Classifier: Programming Language :: Python
Classifier: Programming Language :: Python :: 3
Classifier: Programming Language :: Python :: 3.6
Classifier: Programming Language :: Python :: Implementation :: CPython
Requires-Python: >=3.6.0
Requires-Dist: vak
